stormevents/__init__.py
stormevents/stormevent.py
stormevents/utilities.py
stormevents/nhc/__init__.py
stormevents/nhc/atcf.py
stormevents/nhc/const.py
stormevents/nhc/storms.py
stormevents/nhc/track.py
stormevents/usgs/__init__.py
stormevents/usgs/base.py
stormevents/usgs/events.py
stormevents/usgs/highwatermarks.py
stormevents/usgs/sensors.py
stormevents-2.3.6.dist-info/licenses/LICENSE
stormevents-2.3.6.dist-info/METADATA
stormevents-2.3.6.dist-info/WHEEL
stormevents-2.3.6.dist-info/top_level.txt
stormevents-2.3.6.dist-info/RECORD
