Metadata-Version: 2.4
Name: stormevents
Version: 2.3.6
Summary: Python interfaces for observational data surrounding named storm events
Author-email: Zach Burnett <zachary.r.burnett@gmail.com>, Soroosh Mani <Soroosh.Mani@noaa.gov>
License:                     GNU GENERAL PUBLIC LICENSE
Project-URL: repository, https://github.com/oceanmodeling/StormEvents.git
Project-URL: documentation, https://stormevents.readthedocs.io
Requires-Python: >=3.6
License-File: LICENSE
Requires-Dist: beautifulsoup4
Requires-Dist: geopandas
Requires-Dist: netcdf4
Requires-Dist: numpy
Requires-Dist: python-dateutil
Requires-Dist: pandas
Requires-Dist: pyproj>=2.6
Requires-Dist: requests
Requires-Dist: searvey<1.0,>=0.2.0
Requires-Dist: shapely>=1.8
Requires-Dist: typepigeon<2,>=1.0.5
Requires-Dist: xarray
Provides-Extra: test
Requires-Dist: pytest; extra == "test"
Requires-Dist: pytest-cov; extra == "test"
Requires-Dist: pytest-socket; extra == "test"
Requires-Dist: pytest-xdist; extra == "test"
Provides-Extra: style
Requires-Dist: black; extra == "style"
Requires-Dist: reorder-python-imports; extra == "style"
Provides-Extra: docs
Requires-Dist: dunamai; extra == "docs"
Requires-Dist: m2r2; extra == "docs"
Requires-Dist: sphinx<7; extra == "docs"
Requires-Dist: sphinx-rtd-theme; extra == "docs"
Requires-Dist: toml; extra == "docs"
Dynamic: license-file
